shambolic/__init__.py
shambolic-0.0.0.dist-info/LICENSE
shambolic-0.0.0.dist-info/METADATA
shambolic-0.0.0.dist-info/WHEEL
shambolic-0.0.0.dist-info/top_level.txt
shambolic-0.0.0.dist-info/RECORD
